MANIFEST.in
README.md
requirements.txt
setup.cfg
setup.py
qcloud_cos_py3/__init__.py
qcloud_cos_py3/cos.py
qcloud_cos_py3/cos_auth.py
qcloud_cos_py3.egg-info/PKG-INFO
qcloud_cos_py3.egg-info/SOURCES.txt
qcloud_cos_py3.egg-info/dependency_links.txt
qcloud_cos_py3.egg-info/requires.txt
qcloud_cos_py3.egg-info/top_level.txt