Metadata-Version: 1.1
Name: qcloud-cos-py3
Version: 0.1.4
Summary: A 3rd-party SDK for Qcloud COS and Python 3
Home-page: https://github.com/su27/qcloud_cos_py3
Author: Dan Su
Author-email: damn.su@gmail.com
License: BSD
Download-URL: https://github.com/su27/qcloud_cos_py3/tarball/0.1.4
Keywords: qcloud
Platform: UNKNOWN
Classifier: Development Status :: 3 - Alpha
Classifier: Intended Audience :: Developers
Classifier: Programming Language :: Python :: 3
